Komponenten/RAM/Single_Port_RAM.vhdl
-- Clara Heilig
library ieee;
use ieee.std_logic_1164.all;
use ieee.numeric_std.all;
library work;
use work.constant_package.all;
--use work.types_package.all

-- adr_width auf 16 statt 32. oder wollen die generic?

entity Single_Port_RAM is
    generic(
        G_word_width : integer := WORD_WIDTH;
        G_adr_width : integer := ADR_WIDTH
    );
    port(
        pi_clk : in std_logic;
        pi_rst : in std_logic;
        pi_add : in std_logic_vector (0 to G_adr_width -1); 
        pi_we : in std_logic;
        pi_data : in std_logic_vector(G_word_width -1 downto 0);
        po_data : out std_logic_vector(G_word_width -1 downto 0)
    );
end entity;    

architecture behavior of Single_Port_RAM is
    type memory is array (0 to 2 ** G_adr_width - 1) of std_logic_vector (G_word_width -1 downto 0);
    signal regs : memory := (others => (others => '0'));
    signal add : integer;
    begin
        process(pi_clk, pi_rst, pi_we)
            begin 
            if pi_rst = '1' then 
                regs <= (others => (others => '0'));
                if rising_edge(pi_clk) then 
                    po_data <= (others => '0');
                end if;
            else 
                if rising_edge(pi_clk) then
                    if(pi_we = '1') then
                        regs(to_integer(unsigned(pi_add))) <= pi_data;
                        po_data <= pi_data;    
                    else
                        po_data <= regs(to_integer(unsigned(pi_add)));  
                    end if;            
                end if;            
            end if; 
        end process;
        
    
end behavior;

Testbenches/RAM/Single_Port_RAM_tb.vhdl
-- Clara Heilig
library ieee;
use ieee.std_logic_1164.all;

entity Single_Port_RAM_tb is begin end;

architecture behavior of Single_Port_RAM_tb is
    signal clk : std_logic;
    signal rst : std_logic := '0';
    signal add : std_logic_vector(0 to 15) := (others => '0'); 
    signal data_in :  std_logic_vector(15 downto 0) := (others => '0');
    signal we : std_logic := '0';
    signal data_out : std_logic_vector(15 downto 0);
    constant zero : std_logic_vector(15 downto 0) := (others => '0');
    
    begin
        RAM : entity work.Single_Port_RAM generic map (16, 16) port map (clk, rst, add, we, data_in, data_out);
        clock : process
        begin
            while now < 100 ns loop
                clk <= '0';
                wait for 10 ns;
                clk <= '1';
                wait for 10 ns;    
            end loop;
            wait;
        end process;
                    
        test : process
        begin
            report "RAM Test!";

            --we = 1
            report "reading test starts";
            add <= (others => '0');
            we <= '1';
            data_in(15) <= '1';
            wait for 20 ns;

            assert data_out = data_in report "failure to write"
            severity error;

            -- we = 0  
            report "writing test starts";
            we <= '0';
            wait for 1 ns;
            add(15) <= '1';
            wait for 19 ns;

            assert data_out /= data_in report "wrote while writing flag not set" 
            severity error;

            -- rst
            report "reset test starts";
            add(15) <= '0';
            wait for 20 ns;
            rst <= '1';
            wait for 1 ns;
            wait for 19 ns;
            
            assert data_out = zero report "failed to reset"
            severity error;

            we <= '1';
            wait for 20 ns;
            assert data_out = zero report "wrote while rst = 1"
            severity error;

            report "All tests have finished";
            wait;
        end process;

end behavior;

ram.vcd
$date
  Wed May  7 17:13:47 2025
$end
$version
  GHDL v0
$end
$timescale
  1 fs
$end
$scope module standard $end
$upscope $end
$scope module textio $end
$upscope $end
$scope module std_logic_1164 $end
$upscope $end
$scope module numeric_std $end
$upscope $end
$scope module constant_package $end
$upscope $end
$scope module single_port_ram_tb $end
$var reg 1 ! clk $end
$var reg 1 " rst $end
$var reg 16 # add[0:15] $end
$var reg 16 $ data_in[15:0] $end
$var reg 1 % we $end
$var reg 16 & data_out[15:0] $end
$scope module ram $end
$var reg 1 ' pi_clk $end
$var reg 1 ( pi_rst $end
$var reg 16 ) pi_add[0:15] $end
$var reg 1 * pi_we $end
$var reg 16 + pi_data[15:0] $end
$var reg 16 , po_data[15:0] $end
$comment regs is not handled $end
$var integer 32 - add $end
$upscope $end
$upscope $end
$enddefinitions $end
#0
0!
0"
b0000000000000000 #
b1000000000000000 $
1%
bUUUUUUUUUUUUUUUU &
0'
0(
b0000000000000000 )
1*
b1000000000000000 +
bUUUUUUUUUUUUUUUU ,
b10000000000000000000000000000000 -
#10000000
1!
b1000000000000000 &
1'
b1000000000000000 ,
#20000000
0!
b0000000000000010 #
b0100000000000000 $
0'
b0000000000000010 )
b0100000000000000 +
#30000000
1!
b0100000000000000 &
1'
b0100000000000000 ,
#40000000
0!
0%
0'
0*
#41000000
b0000000000000000 #
b0000000000000000 )
#50000000
1!
b1000000000000000 &
1'
b1000000000000000 ,
#60000000
0!
b0000000000000001 #
0'
b0000000000000001 )
#70000000
1!
b0000000000000000 &
1'
b0000000000000000 ,
#80000000
0!
b0000000000000000 #
0'
b0000000000000000 )
#90000000
1!
b1000000000000000 &
1'
b1000000000000000 ,
#100000000
0!
1"
0'
1(
#110000000
1!
b0000000000000000 &
1'
b0000000000000000 ,
#120000000
0!
b0000000000000010 #
0'
b0000000000000010 )
#130000000
1!
1'
#140000000
0!
1%
0'
1*
