Komponenten/Decoder/decoder.vhdl
-- Laboratory RA solutions/versuch3
-- Sommersemester 25
-- Group Details
-- Lab Date:
-- 1. Participant First and Last Name: 
-- 2. Participant First and Last Name:

library ieee;
use ieee.std_logic_1164.all;
use ieee.numeric_std.all;
use work.Constant_package.all;
use work.types.all;

entity decoder is
    generic (
        G_WORD_WIDTH : integer := 32
    );
    port(
        pi_clk : in std_logic;
        pi_instruction : in std_logic_vector(G_WORD_WIDTH - 1 downto 0);
        po_controlWord : out controlword := control_word_init
    );
end entity decoder;

architecture arc of decoder is
    begin
        process(pi_instruction, pi_clk)
            variable opcode : std_logic_vector(OPCODE_WIDTH - 1 downto 0);
            variable funct3 : std_logic_vector(2 downto 0);
            variable funct7 : std_logic_vector(6 downto 0);
        begin
            if rising_edge(pi_clk) then
                opcode := pi_instruction(6 downto 0);
                funct3 := pi_instruction(14 downto 12);
                funct7 := pi_instruction(31 downto 25);

                -- decoding the opcode component of the incomming instruction

                case opcode is
                    when R_INS_OP => 
                        -- register operations (r_type) set the alu_opcode based on the operation (func3) and the selector bit (func7(1))
                        -- the immediate select bit of the alu input mux is cleared since both inputs are registers
                        po_controlWord.ALU_OP <= funct7(5) & funct3;
                        po_controlWord.I_IMM_SEL <= '0';
                    when I_INS_OP =>
                        
                    when L_INS_OP =>
                        
                    when S_INS_OP =>
                        
                    when B_INS_OP =>
                        
                    when JAL_INS_OP =>
                        
                    when JALR_INS_OP =>
                        
                    when LUI_INS_OP =>
                        
                    when AUIPC_INS_OP =>

                    when others =>
                        po_controlWord <= control_word_init;
                end case;
            end if;
        end process;
end architecture;

Testbenches/Decoder/decoder_tb.vhdl
-- Laboratory RA solutions/versuch3
-- Sommersemester 25
-- Group Details
-- Lab Date:
-- 1. Participant First and Last Name: 
-- 2. Participant First and Last Name:

library ieee;
use ieee.std_logic_1164.all;
use ieee.numeric_std.all;
use work.constant_package.all;
use work.types.all;
use ieee.std_logic_textio.all;

entity decoder_tb is
end entity decoder_tb;

architecture behavior of decoder_tb is

  constant PERIOD      : time                                      := 10 ns; -- Example: ClockPERIOD of 10 ns
  signal s_instruction : std_logic_vector(31 downto 0) := (others => '0');
  signal s_controlword : controlWord                               := CONTROL_WORD_INIT;
  signal s_clk         : std_logic                                 := '0';

begin

  lu8 : entity work.decoder
    port map
    (
      pi_instruction => s_instruction,
      po_controlWord => s_controlword,
      pi_clk         => s_clk
    );

  lu : process is

    -- For each architecture, check if the instruction format it adds to the decoder is decoded correctly

    variable v_aluoperation        : std_logic_vector(ALU_OPCODE_WIDTH - 1 downto 0) := ADD_ALU_OP;
    variable v_rs1                 : integer                                         := 5;
    variable v_rs2                 : integer                                         := 4;
    variable v_rd                  : integer                                         := 6;
    variable v_expectedcontrolword : controlWord                                     := CONTROL_WORD_INIT;
    variable instr                 : std_logic_vector(WORD_WIDTH - 1 downto 0)       := (others => '0');
    variable func7                 : std_logic_vector(6 downto 0)                    := "0" & ADD_ALU_OP (ALU_OPCODE_WIDTH - 1) & "00000";
    variable func3                 : std_logic_vector(2 downto 0)                    := ADD_ALU_OP(ALU_OPCODE_WIDTH - 2 downto 0);

  begin

    -- R-Format Decoding
    instr := (others => '0');
    func7 := "0" & ADD_ALU_OP (ALU_OPCODE_WIDTH - 1) & "00000";
    func3 := ADD_ALU_OP(ALU_OPCODE_WIDTH - 2 downto 0);
    s_instruction <= func7 & std_logic_vector(to_unsigned(v_rs2, REG_ADR_WIDTH)) & std_logic_vector(to_unsigned(v_rs1, REG_ADR_WIDTH)) & func3 & std_logic_vector(to_unsigned(v_rd, REG_ADR_WIDTH)) & R_INS_OP; -- R-Befehle haben alle den gleichen Opcode, daher hier hardkodiert

    v_expectedControlWord.I_IMM_SEL := '0';
    v_expectedControlWord.ALU_OP    := ADD_ALU_OP;
    s_clk <= '1';
    wait for PERIOD / 2;
    s_clk <= '0';
    wait for PERIOD / 2;
    assert (s_controlword = v_expectedcontrolword)
    report "Error in R-Format decoding with alu_op: " & to_string(s_controlword.ALU_OP) & " and i_imm_sel: " & std_logic'image(s_controlword.I_IMM_SEL) 
    & " expected alu_op: " & to_string(v_expectedControlWord.ALU_OP) & " and i_imm_sel: " & std_logic'image(v_expectedControlWord.I_IMM_SEL) 
    severity error;

    instr := (others => '0');
    func7 := "0" & SUB_ALU_OP (ALU_OPCODE_WIDTH - 1) & "00000";
    func3 := SUB_ALU_OP(ALU_OPCODE_WIDTH - 2 downto 0);
    s_instruction <= func7 & std_logic_vector(to_unsigned(v_rs2, REG_ADR_WIDTH)) & std_logic_vector(to_unsigned(v_rs1, REG_ADR_WIDTH)) & func3 & std_logic_vector(to_unsigned(v_rd, REG_ADR_WIDTH)) & R_INS_OP; -- R-Befehle haben alle den gleichen Opcode, daher hier hardkodiert

    v_expectedControlWord.I_IMM_SEL := '0';
    v_expectedControlWord.ALU_OP    := SUB_ALU_OP;
    s_clk <= '1';
    wait for PERIOD / 2;
    s_clk <= '0';
    wait for PERIOD / 2;
    assert (s_controlword = v_expectedcontrolword)
    report "Error in R-Format decoding at SUB_ALU_OP with alu_op: " & to_string(s_controlword.ALU_OP) & " and i_imm_sel: " & std_logic'image(s_controlword.I_IMM_SEL)
    & " expected alu_op: " & to_string(v_expectedControlWord.ALU_OP) & " and i_imm_sel: " & std_logic'image(v_expectedControlWord.I_IMM_SEL) 
    severity error;

    instr := (others => '0');
    func7 := "0" & SRA_ALU_OP (ALU_OPCODE_WIDTH - 1) & "00000";
    func3 := SRA_ALU_OP(ALU_OPCODE_WIDTH - 2 downto 0);
    s_instruction <= func7 & std_logic_vector(to_unsigned(v_rs2, REG_ADR_WIDTH)) & std_logic_vector(to_unsigned(v_rs1, REG_ADR_WIDTH)) & func3 & std_logic_vector(to_unsigned(v_rd, REG_ADR_WIDTH)) & R_INS_OP; -- R-Befehle haben alle den gleichen Opcode, daher hier hardkodiert

    v_expectedControlWord.I_IMM_SEL := '0';
    v_expectedControlWord.ALU_OP    := SRA_ALU_OP;
    s_clk <= '1';
    wait for PERIOD / 2;
    s_clk <= '0';
    wait for PERIOD / 2;
    assert (s_controlword = v_expectedcontrolword)
    report "Error in R-Format decoding at SRA with alu_op: " & to_string(s_controlword.ALU_OP) & " and i_imm_sel: " & std_logic'image(s_controlword.I_IMM_SEL)
    & " expected alu_op: " & to_string(v_expectedControlWord.ALU_OP) & " and i_imm_sel: " & std_logic'image(v_expectedControlWord.I_IMM_SEL) 
    severity error;
    instr := (others => '0');
    func7 := "0" & SRL_ALU_OP (ALU_OPCODE_WIDTH - 1) & "00000";
    func3 := SRL_ALU_OP(ALU_OPCODE_WIDTH - 2 downto 0);
    s_instruction <= func7 & std_logic_vector(to_unsigned(v_rs2, REG_ADR_WIDTH)) & std_logic_vector(to_unsigned(v_rs1, REG_ADR_WIDTH)) & func3 & std_logic_vector(to_unsigned(v_rd, REG_ADR_WIDTH)) & R_INS_OP; -- R-Befehle haben alle den gleichen Opcode, daher hier hardkodiert

    v_expectedControlWord.I_IMM_SEL := '0';
    v_expectedControlWord.ALU_OP    := SRL_ALU_OP;
    s_clk <= '1';
    wait for PERIOD / 2;
    s_clk <= '0';
    wait for PERIOD / 2;
    assert (s_controlword = v_expectedcontrolword)
    report "Error in R-Format decoding at SRL with alu_op: " & to_string(s_controlword.ALU_OP) & " and i_imm_sel: " & std_logic'image(s_controlword.I_IMM_SEL)
    & " expected alu_op: " & to_string(v_expectedControlWord.ALU_OP) & " and i_imm_sel: " & std_logic'image(v_expectedControlWord.I_IMM_SEL) 
    severity error;
    instr := (others => '0');
    func7 := "0" & SLL_ALU_OP (ALU_OPCODE_WIDTH - 1) & "00000";
    func3 := SLL_ALU_OP(ALU_OPCODE_WIDTH - 2 downto 0);
    s_instruction <= func7 & std_logic_vector(to_unsigned(v_rs2, REG_ADR_WIDTH)) & std_logic_vector(to_unsigned(v_rs1, REG_ADR_WIDTH)) & func3 & std_logic_vector(to_unsigned(v_rd, REG_ADR_WIDTH)) & R_INS_OP; -- R-Befehle haben alle den gleichen Opcode, daher hier hardkodiert

    v_expectedControlWord.I_IMM_SEL := '0';
    v_expectedControlWord.ALU_OP    := SLL_ALU_OP;
    s_clk <= '1';
    wait for PERIOD / 2;
    s_clk <= '0';
    wait for PERIOD / 2;
    assert (s_controlword = v_expectedcontrolword)
    report "Error in R-Format decoding at SLL with alu_op: " & to_string(s_controlword.ALU_OP) & " and i_imm_sel: " & std_logic'image(s_controlword.I_IMM_SEL)
    & " expected alu_op: " & to_string(v_expectedControlWord.ALU_OP) & " and i_imm_sel: " & std_logic'image(v_expectedControlWord.I_IMM_SEL) 
    severity error;
    instr := (others => '0');
    func7 := "0" & OR_ALU_OP (ALU_OPCODE_WIDTH - 1) & "00000";
    func3 := OR_ALU_OP(ALU_OPCODE_WIDTH - 2 downto 0);
    s_instruction <= func7 & std_logic_vector(to_unsigned(v_rs2, REG_ADR_WIDTH)) & std_logic_vector(to_unsigned(v_rs1, REG_ADR_WIDTH)) & func3 & std_logic_vector(to_unsigned(v_rd, REG_ADR_WIDTH)) & R_INS_OP; -- R-Befehle haben alle den gleichen Opcode, daher hier hardkodiert

    v_expectedControlWord.I_IMM_SEL := '0';
    v_expectedControlWord.ALU_OP    := OR_ALU_OP;
    s_clk <= '1';
    wait for PERIOD / 2;
    s_clk <= '0';
    wait for PERIOD / 2;
    assert (s_controlword = v_expectedcontrolword)
    report "Error in R-Format decoding at OR with alu_op: " & to_string(s_controlword.ALU_OP) & " and i_imm_sel: " & std_logic'image(s_controlword.I_IMM_SEL)
    & " expected alu_op: " & to_string(v_expectedControlWord.ALU_OP) & " and i_imm_sel: " & std_logic'image(v_expectedControlWord.I_IMM_SEL) 
    severity error;
    instr := (others => '0');
    func7 := "0" & XOR_ALU_OP (ALU_OPCODE_WIDTH - 1) & "00000";
    func3 := XOR_ALU_OP(ALU_OPCODE_WIDTH - 2 downto 0);
    s_instruction <= func7 & std_logic_vector(to_unsigned(v_rs2, REG_ADR_WIDTH)) & std_logic_vector(to_unsigned(v_rs1, REG_ADR_WIDTH)) & func3 & std_logic_vector(to_unsigned(v_rd, REG_ADR_WIDTH)) & R_INS_OP; -- R-Befehle haben alle den gleichen Opcode, daher hier hardkodiert

    v_expectedControlWord.I_IMM_SEL := '0';
    v_expectedControlWord.ALU_OP    := XOR_ALU_OP;
    s_clk <= '1';
    wait for PERIOD / 2;
    s_clk <= '0';
    wait for PERIOD / 2;
    assert (s_controlword = v_expectedcontrolword)
    report "Error in R-Format decoding at XOR with alu_op: " & to_string(s_controlword.ALU_OP) & " and i_imm_sel: " & std_logic'image(s_controlword.I_IMM_SEL)
    & " expected alu_op: " & to_string(v_expectedControlWord.ALU_OP) & " and i_imm_sel: " & std_logic'image(v_expectedControlWord.I_IMM_SEL) 
    severity error;
    instr := (others => '0');
    func7 := "0" & AND_ALU_OP (ALU_OPCODE_WIDTH - 1) & "00000";
    func3 := AND_ALU_OP(ALU_OPCODE_WIDTH - 2 downto 0);
    s_instruction <= func7 & std_logic_vector(to_unsigned(v_rs2, REG_ADR_WIDTH)) & std_logic_vector(to_unsigned(v_rs1, REG_ADR_WIDTH)) & func3 & std_logic_vector(to_unsigned(v_rd, REG_ADR_WIDTH)) & R_INS_OP; -- R-Befehle haben alle den gleichen Opcode, daher hier hardkodiert

    v_expectedControlWord.I_IMM_SEL := '0';
    v_expectedControlWord.ALU_OP    := AND_ALU_OP;
    s_clk <= '1';
    wait for PERIOD / 2;
    s_clk <= '0';
    wait for PERIOD / 2;
    assert (s_controlword = v_expectedcontrolword)
    report "Error in R-Format decoding at AND with alu_op: " & to_string(s_controlword.ALU_OP) & " and i_imm_sel: " & std_logic'image(s_controlword.I_IMM_SEL)
    & " expected alu_op: " & to_string(v_expectedControlWord.ALU_OP) & " and i_imm_sel: " & std_logic'image(v_expectedControlWord.I_IMM_SEL) 
    severity error;

    instr := (others => '0');
    func7 := "0" & "0" & "00000";
    func3 := "011";
    s_instruction <= func7 & std_logic_vector(to_unsigned(v_rs2, REG_ADR_WIDTH)) & std_logic_vector(to_unsigned(v_rs1, REG_ADR_WIDTH)) & func3 & std_logic_vector(to_unsigned(v_rd, REG_ADR_WIDTH)) & "0000011"; -- R-Befehle haben alle den gleichen Opcode, daher hier hardkodiert

    v_expectedControlWord.I_IMM_SEL := '0';
    v_expectedControlWord.ALU_OP    := "0000";
    s_clk <= '1';
    wait for PERIOD / 2;
    s_clk <= '0';
    wait for PERIOD / 2;
    assert (s_controlword = v_expectedcontrolword)
    report "Error in R-Format decoding at NOP with alu_op: " & to_string(s_controlword.ALU_OP) & " and i_imm_sel: " & std_logic'image(s_controlword.I_IMM_SEL)
    & " expected alu_op: " & to_string(v_expectedControlWord.ALU_OP) & " and i_imm_sel: " & std_logic'image(v_expectedControlWord.I_IMM_SEL) 
    severity error;

    assert false
    report "end of test"
      severity note;

    wait; --  Wait forever; this will finish the simulation.

  end process lu;

end architecture behavior;

reg.vcd
$date
  Fri May 09 15:45:50 2025
$end
$version
  GHDL v0
$end
$timescale
  1 fs
$end
$scope module standard $end
$upscope $end
$scope module textio $end
$upscope $end
$scope module std_logic_1164 $end
$upscope $end
$scope module numeric_std $end
$upscope $end
$scope module constant_package $end
$upscope $end
$scope module types $end
$upscope $end
$scope module std_logic_textio $end
$upscope $end
$scope module decoder_tb $end
$var reg 32 ! s_instruction[31:0] $end
$comment s_controlword is not handled $end
$var reg 1 " s_clk $end
$scope module lu8 $end
$var reg 1 # pi_clk $end
$var reg 32 $ pi_instruction[31:0] $end
$comment po_controlword is not handled $end
$upscope $end
$upscope $end
$enddefinitions $end
#0
b00000000010000101000001100110011 !
1"
1#
b00000000010000101000001100110011 $
#5000000
0"
0#
#10000000
b01000000010000101000001100110011 !
1"
1#
b01000000010000101000001100110011 $
#15000000
0"
0#
#20000000
b01000000010000101101001100110011 !
1"
1#
b01000000010000101101001100110011 $
#25000000
0"
0#
#30000000
b00000000010000101101001100110011 !
1"
1#
b00000000010000101101001100110011 $
#35000000
0"
0#
#40000000
b00000000010000101001001100110011 !
1"
1#
b00000000010000101001001100110011 $
#45000000
0"
0#
#50000000
b00000000010000101110001100110011 !
1"
1#
b00000000010000101110001100110011 $
#55000000
0"
0#
#60000000
b00000000010000101100001100110011 !
1"
1#
b00000000010000101100001100110011 $
#65000000
0"
0#
#70000000
b00000000010000101111001100110011 !
1"
1#
b00000000010000101111001100110011 $
#75000000
0"
0#
#80000000
b00000000010000101011001100000011 !
1"
1#
b00000000010000101011001100000011 $
