Komponenten/Registerfile/Register_File.vhdl
-- Paul Riedel
library ieee;
use ieee.std_logic_1164.all;
use work.types_package.all;
use work.constant_package.all;
use ieee.numeric_std.all;

entity register_file is 
    generic (
        G_WORD_WIDTH : integer := WORD_WIDTH; 
        G_REG_ADR_WIDTH : integer := 4
    );
    port (
        pi_clk, pi_rst, pi_writeEnable : in std_logic;
        pi_writeRegData : in std_logic_vector ((G_WORD_WIDTH -1) downto 0);
        pi_readRegAddr1, pi_readRegAddr2, pi_writeRegAddr : in std_logic_vector ((G_REG_ADR_WIDTH -1) downto 0);
        po_readRegData1, po_readRegData2 : out std_logic_vector ((G_WORD_WIDTH -1) downto 0)
    );
end register_file;

-- architecture behaviour of register_file is 
--     signal s_write : std_logic_vector (G_WORD_WIDTH - 1 downto 0);
--     signal s_zeros : std_logic_vector (G_REG_ADR_WIDTH - 1 downto 0);
-- begin
--         s_write <= pi_writeRegData when pi_writeEnable = '1';
--         po_readRegData1 <= (others => '0') when pi_readRegAddr1 = s_zeros and rising_edge(pi_clk) else 
--                     (others => 'Z');
--         po_readRegData2 <= (others => '0') when pi_readRegAddr2 = s_zeros and rising_edge(pi_clk) else   
--                     (others => 'Z');
--         registers : for i in 1 to 2 ** G_REG_ADR_WIDTH generate
--                 reg : entity work.addressable_register generic map(G_WORD_WIDTH, G_REG_ADR_WIDTH, i) port map(pi_clk, pi_rst, s_write, pi_readRegAddr1, pi_readRegAddr2, pi_writeRegAddr, po_readRegData1, po_readRegData2);
--         end generate;
-- end architecture;

architecture behavior of register_file is

    signal s_storage : registermemory := (others => (others => '0'));
    begin
        process(pi_clk, pi_rst)
        begin
            if pi_rst = '1' then
                s_storage <= (others => (others => '0'));
            else if rising_edge(pi_clk) then
                if pi_writeEnable = '1' and (to_integer(unsigned(pi_writeRegAddr)) /= 0) then 
                    s_storage(to_integer(unsigned(pi_writeRegAddr))) <= pi_writeRegData;
                end if;
                end if;
            end if;
            po_readRegData1 <= s_storage(to_integer(unsigned(pi_readRegAddr1)));
            po_readRegData2 <= s_storage(to_integer(unsigned(pi_readRegAddr2)));
        end process;

end architecture;

Testbenches/Registerfile/register_file_tb.vhdl
library ieee;
use ieee.std_logic_1164.all;
use ieee.numeric_std.all;
use ieee.math_real.all;

use work.constant_package.all;

entity register_file_tb is
     generic (G_WORD_WIDTH : integer := 16); 
end entity register_file_tb;

architecture behav of register_file_tb is

signal s_we, s_rst, s_clk : std_logic := '0';
signal s_adr1, s_adr2, s_adrWr : std_logic_vector(REG_ADR_WIDTH - 1 downto 0) := (others => '0');

signal s_reg1, s_reg2, s_reg3 : std_logic_vector(G_WORD_WIDTH - 1 downto 0) := (others => '0');
begin 
dut1 : entity work.register_file
    generic map (G_WORD_WIDTH, REG_ADR_WIDTH)
    port map(
        pi_readRegAddr1 => s_adr1,
        pi_readRegAddr2 => s_adr2,
        pi_writeRegAddr => s_adrWr,
        po_readRegData1 => s_reg1,
        po_readRegData2 => s_reg2,
        pi_writeRegData => s_reg3,
        pi_clk => s_clk,
        pi_writeEnable => s_we,
        pi_rst => s_rst 
    );

test: process is
begin
    report "test begin";
    
    s_we <= '1';
    s_adrWr <= "00100";
    s_reg3 <= std_logic_vector(to_unsigned(7, G_WORD_WIDTH));

    s_clk <= '0';
    wait for 1 ns;
    s_clk <= '1';
    wait for 1 ns;

    s_adr1 <= "00100";

    s_clk <= '0';
    wait for 1 ns;
    s_clk <= '1';
    wait for 1 ns;

    s_adrWr <= "00101";
    s_reg3 <= std_logic_vector(to_unsigned(13, G_WORD_WIDTH));

    s_clk <= '0';
    wait for 1 ns;
    s_clk <= '1';
    wait for 1 ns;

    s_adr2 <= "00101";

    s_clk <= '0';
    wait for 1 ns;
    s_clk <= '1';
    wait for 1 ns;

    assert s_reg1 = std_logic_vector(to_unsigned(7, G_WORD_WIDTH)) and s_reg2 = std_logic_vector(to_unsigned(13, G_WORD_WIDTH))
    report "value is read incorrectly"
    severity error;

    -- write to R0

    s_adrWr <= "00000";
    s_reg3 <= std_logic_vector(to_unsigned(35, G_WORD_WIDTH));

    s_clk <= '0';
    wait for 1 ns;
    s_clk <= '1';
    wait for 1 ns;

    s_adr1 <= "00000";
    
    s_clk <= '0';
    wait for 1 ns;
    s_clk <= '1';
    wait for 1 ns;

    assert s_reg1 = std_logic_vector(to_unsigned(0, G_WORD_WIDTH))
    report "R0 writes to non zero after write"
    severity error;

    -- reset

    s_rst <= '1';

    s_clk <= '0';
    wait for 1 ns;
    s_clk <= '1';
    wait for 1 ns;

    assert s_reg2 = std_logic_vector(to_unsigned(0, G_WORD_WIDTH))
    report "reset does not work"
    severity error;

    s_clk <= '0';
    wait for 1 ns;
    s_clk <= '1';
    wait for 1 ns;

    assert s_reg2 = std_logic_vector(to_unsigned(0, G_WORD_WIDTH))
    report "write during reset possible"
    severity error;

    s_rst <= '0';
    s_we <= '0';

    s_clk <= '0';
    wait for 1 ns;
    s_clk <= '1';
    wait for 1 ns;

    assert s_reg2 = std_logic_vector(to_unsigned(0, G_WORD_WIDTH))
    report "write without w_enable"
    severity error;

    -- write after reset

    s_we <= '1';
    s_clk <= '0';
    wait for 1 ns;
    s_clk <= '1';
    wait for 1 ns;

    s_adrWr <= "00101";
    s_reg3 <= std_logic_vector(to_unsigned(13, G_WORD_WIDTH));

    s_clk <= '0';
    wait for 1 ns;
    s_clk <= '1';
    wait for 1 ns;

    s_adr2 <= "00101";

    s_clk <= '0';
    wait for 1 ns;
    s_clk <= '1';
    wait for 1 ns;

    assert s_reg2 = std_logic_vector(to_unsigned(13, G_WORD_WIDTH))
    report "write after reset not possible"
    severity error;

    report "all tests finished";

    wait;
end process;

end architecture;

reg.vcd
$date
  Wed May 07 17:23:52 2025
$end
$version
  GHDL v0
$end
$timescale
  1 fs
$end
$scope module standard $end
$upscope $end
$scope module textio $end
$upscope $end
$scope module std_logic_1164 $end
$upscope $end
$scope module numeric_std $end
$upscope $end
$scope module math_real $end
$upscope $end
$scope module constant_package $end
$upscope $end
$scope module types_package $end
$upscope $end
$scope module register_file_tb $end
$var reg 1 ! s_we $end
$var reg 1 " s_rst $end
$var reg 1 # s_clk $end
$var reg 5 $ s_adr1[4:0] $end
$var reg 5 % s_adr2[4:0] $end
$var reg 5 & s_adrwr[4:0] $end
$var reg 16 ' s_reg1[15:0] $end
$var reg 16 ( s_reg2[15:0] $end
$var reg 16 ) s_reg3[15:0] $end
$scope module dut1 $end
$var reg 1 * pi_clk $end
$var reg 1 + pi_rst $end
$var reg 1 , pi_writeenable $end
$var reg 16 - pi_writeregdata[15:0] $end
$var reg 5 . pi_readregaddr1[4:0] $end
$var reg 5 / pi_readregaddr2[4:0] $end
$var reg 5 0 pi_writeregaddr[4:0] $end
$var reg 16 1 po_readregdata1[15:0] $end
$var reg 16 2 po_readregdata2[15:0] $end
$comment s_storage is not handled $end
$upscope $end
$upscope $end
$enddefinitions $end
#0
1!
0"
0#
b00000 $
b00000 %
b00100 &
b0000000000000000 '
b0000000000000000 (
b0000000000000111 )
0*
0+
1,
b0000000000000111 -
b00000 .
b00000 /
b00100 0
b0000000000000000 1
b0000000000000000 2
#1000000
1#
1*
#2000000
0#
b00100 $
b0000000000000111 '
0*
b00100 .
b0000000000000111 1
#3000000
1#
1*
#4000000
0#
b00101 &
b0000000000001101 )
0*
b0000000000001101 -
b00101 0
#5000000
1#
1*
#6000000
0#
b00101 %
b0000000000001101 (
0*
b00101 /
b0000000000001101 2
#7000000
1#
1*
#8000000
0#
b00000 &
b0000000000100011 )
0*
b0000000000100011 -
b00000 0
#9000000
1#
1*
#10000000
0#
b00000 $
b0000000000000000 '
0*
b00000 .
b0000000000000000 1
#11000000
1#
1*
#12000000
1"
0#
0*
1+
#13000000
1#
b0000000000000000 (
1*
b0000000000000000 2
#14000000
0#
0*
#15000000
1#
1*
#16000000
0!
0"
0#
0*
0+
0,
#17000000
1#
1*
#18000000
1!
0#
0*
1,
#19000000
1#
1*
#20000000
0#
b00101 &
b0000000000001101 )
0*
b0000000000001101 -
b00101 0
#21000000
1#
1*
#22000000
0#
b0000000000001101 (
0*
b0000000000001101 2
